uipath/__init__.py
uipath/_config.py
uipath/_execution_context.py
uipath/_folder_context.py
uipath/_uipath.py
uipath/py.typed
uipath/_cli/README.md
uipath/_cli/__init__.py
uipath/_cli/cli_auth.py
uipath/_cli/cli_deploy.py
uipath/_cli/cli_init.py
uipath/_cli/cli_invoke.py
uipath/_cli/cli_new.py
uipath/_cli/cli_pack.py
uipath/_cli/cli_publish.py
uipath/_cli/cli_run.py
uipath/_cli/middlewares.py
uipath/_cli/spinner.py
uipath/_cli/_auth/_auth_server.py
uipath/_cli/_auth/_models.py
uipath/_cli/_auth/_oidc_utils.py
uipath/_cli/_auth/_portal_service.py
uipath/_cli/_auth/_utils.py
uipath/_cli/_auth/auth_config.json
uipath/_cli/_auth/index.html
uipath/_cli/_auth/localhost.crt
uipath/_cli/_auth/localhost.key
uipath/_cli/_runtime/_contracts.py
uipath/_cli/_runtime/_hitl.py
uipath/_cli/_runtime/_logging.py
uipath/_cli/_runtime/_runtime.py
uipath/_cli/_templates/.psmdcp.template
uipath/_cli/_templates/.rels.template
uipath/_cli/_templates/[Content_Types].xml.template
uipath/_cli/_templates/main.py.template
uipath/_cli/_templates/package.nuspec.template
uipath/_cli/_utils/_common.py
uipath/_cli/_utils/_console.py
uipath/_cli/_utils/_constants.py
uipath/_cli/_utils/_folders.py
uipath/_cli/_utils/_input_args.py
uipath/_cli/_utils/_parse_ast.py
uipath/_cli/_utils/_processes.py
uipath/_cli/_utils/_tracing.py
uipath/_services/__init__.py
uipath/_services/_base_service.py
uipath/_services/actions_service.py
uipath/_services/api_client.py
uipath/_services/assets_service.py
uipath/_services/attachments_service.py
uipath/_services/buckets_service.py
uipath/_services/connections_service.py
uipath/_services/context_grounding_service.py
uipath/_services/folder_service.py
uipath/_services/jobs_service.py
uipath/_services/llm_gateway_service.py
uipath/_services/processes_service.py
uipath/_services/queues_service.py
uipath/_utils/__init__.py
uipath/_utils/_endpoint.py
uipath/_utils/_infer_bindings.py
uipath/_utils/_logs.py
uipath/_utils/_read_overwrites.py
uipath/_utils/_request_override.py
uipath_nightly-2.0.63.dev1003960402.dist-info/METADATA
uipath_nightly-2.0.63.dev1003960402.dist-info/WHEEL
uipath_nightly-2.0.63.dev1003960402.dist-info/entry_points.txt
uipath_nightly-2.0.63.dev1003960402.dist-info/licenses/LICENSE
uipath_nightly-2.0.63.dev1003960402.dist-info/RECORD
