Metadata-Version: 2.4
Name: uipath-nightly
Version: 2.0.63.dev1003960402
Summary: Python SDK and CLI for UiPath Platform, enabling programmatic interaction with automation services, process management, and deployment tools.
Project-URL: Homepage, https://uipath.com
Project-URL: Repository, https://github.com/UiPath/uipath-python
Project-URL: Documentation, https://uipath.github.io/uipath-python/
Maintainer-email: Marius Cosareanu <marius.cosareanu@uipath.com>, Cristian Pufu <cristian.pufu@uipath.com>
License-File: LICENSE
Classifier: Development Status :: 3 - Alpha
Classifier: Intended Audience :: Developers
Classifier: Programming Language :: Python :: 3.10
Classifier: Programming Language :: Python :: 3.11
Classifier: Programming Language :: Python :: 3.12
Classifier: Topic :: Software Development :: Build Tools
Requires-Python: >=3.10
Requires-Dist: azure-monitor-opentelemetry>=1.6.8
Requires-Dist: click>=8.1.8
Requires-Dist: httpx>=0.28.1
Requires-Dist: opentelemetry-sdk>=1.31.1
Requires-Dist: pathlib>=1.0.1
Requires-Dist: pydantic>=2.11.1
Requires-Dist: python-dotenv>=1.0.1
Requires-Dist: rich>=13.0.0
Requires-Dist: tenacity>=9.0.0
Requires-Dist: tomli>=2.2.1
Provides-Extra: langchain
Requires-Dist: uipath-langchain<0.1.0,>=0.0.88; extra == 'langchain'
